{
  "statistics": {
    "config": "trinity-no-cgate",
    "attack": "executor-flip",
    "corruption_rate": 0.1,
    "split": "test",
    "seed": 999,
    "n_timesteps": 116,
    "sharpe_ratio": 1.2463896354328226,
    "sortino_ratio": 1.830936311257792,
    "total_return": 0.06808817744130136,
    "max_drawdown": 0.06718927985079093,
    "final_portfolio_value": 106808.81774413015
  },
  "results": [
    {
      "date": "2024-07-16",
      "action": 1,
      "position_scale": 0.5,
      "effective_position": 0.5,
      "step_return": -0.0,
      "portfolio_value": 100000.0
    },
    {
      "date": "2024-07-17",
      "action": 1,
      "position_scale": 1.0,
      "effective_position": 1.0,
      "step_return": -0.010267380174931931,
      "portfolio_value": 98973.26198250681
    },
    {
      "date": "2024-07-18",
      "action": 1,
      "position_scale": 0.5,
      "effective_position": 0.5,
      "step_return": 0.0005798023555079441,
      "portfolio_value": 99030.64691293657
    },
    {
      "date": "2024-07-19",
      "action": 1,
      "position_scale": 0.5,
      "effective_position": 0.5,
      "step_return": -0.0007801510862783829,
      "portfolio_value": 98953.3880461726
    },
    {
      "date": "2024-07-22",
      "action": 1,
      "position_scale": 0.5,
      "effective_position": 0.5,
      "step_return": 0.002344145109324551,
      "portfolio_value": 99185.34914681212
    },
    {
      "date": "2024-07-23",
      "action": 0,
      "position_scale": 1.0,
      "effective_position": 0.0,
      "step_return": -0.014377114814227106,
      "portfolio_value": 97759.34999423921
    },
    {
      "date": "2024-07-24",
      "action": 1,
      "position_scale": 0.5,
      "effective_position": 0.5,
      "step_return": -0.0,
      "portfolio_value": 97759.34999423921
    },
    {
      "date": "2024-07-25",
      "action": 1,
      "position_scale": 0.5,
      "effective_position": 0.5,
      "step_return": 0.001080490821749239,
      "portfolio_value": 97864.97807464816
    },
    {
      "date": "2024-07-26",
      "action": 0,
      "position_scale": 1.0,
      "effective_position": 0.0,
      "step_return": 0.000642346168498582,
      "portfolio_value": 97927.84126834461
    },
    {
      "date": "2024-07-29",
      "action": 0,
      "position_scale": 1.0,
      "effective_position": 0.0,
      "step_return": 0.0,
      "portfolio_value": 97927.84126834461
    },
    {
      "date": "2024-07-30",
      "action": 0,
      "position_scale": 1.0,
      "effective_position": 0.0,
      "step_return": 0.0,
      "portfolio_value": 97927.84126834461
    },
    {
      "date": "2024-07-31",
      "action": 0,
      "position_scale": 1.0,
      "effective_position": 0.0,
      "step_return": -0.0,
      "portfolio_value": 97927.84126834461
    },
    {
      "date": "2024-08-01",
      "action": 0,
      "position_scale": 0.5,
      "effective_position": 0.0,
      "step_return": 0.0,
      "portfolio_value": 97927.84126834461
    },
    {
      "date": "2024-08-02",
      "action": 0,
      "position_scale": 1.0,
      "effective_position": 0.0,
      "step_return": -0.0,
      "portfolio_value": 97927.84126834461
    },
    {
      "date": "2024-08-05",
      "action": 0,
      "position_scale": 1.0,
      "effective_position": 0.0,
      "step_return": -0.0,
      "portfolio_value": 97927.84126834461
    },
    {
      "date": "2024-08-06",
      "action": 0,
      "position_scale": 1.0,
      "effective_position": 0.0,
      "step_return": 0.0,
      "portfolio_value": 97927.84126834461
    },
    {
      "date": "2024-08-07",
      "action": 1,
      "position_scale": 0.5,
      "effective_position": 0.5,
      "step_return": 0.0,
      "portfolio_value": 97927.84126834461
    },
    {
      "date": "2024-08-08",
      "action": 2,
      "position_scale": 0.5,
      "effective_position": -0.5,
      "step_return": 0.0068679820507162636,
      "portfolio_value": 98600.407924441
    },
    {
      "date": "2024-08-09",
      "action": 0,
      "position_scale": 1.0,
      "effective_position": 0.0,
      "step_return": -0.0035649156690247884,
      "portfolio_value": 98248.90578525892
    },
    {
      "date": "2024-08-12",
      "action": 0,
      "position_scale": 0.5,
      "effective_position": 0.0,
      "step_return": 0.0,
      "portfolio_value": 98248.90578525892
    },
    {
      "date": "2024-08-13",
      "action": 0,
      "position_scale": 1.0,
      "effective_position": 0.0,
      "step_return": 0.0,
      "portfolio_value": 98248.90578525892
    },
    {
      "date": "2024-08-14",
      "action": 0,
      "position_scale": 1.0,
      "effective_position": 0.0,
      "step_return": 0.0,
      "portfolio_value": 98248.90578525892
    },
    {
      "date": "2024-08-15",
      "action": 2,
      "position_scale": 0.5,
      "effective_position": -0.5,
      "step_return": 0.0,
      "portfolio_value": 98248.90578525892
    },
    {
      "date": "2024-08-16",
      "action": 0,
      "position_scale": 1.0,
      "effective_position": 0.0,
      "step_return": 0.00035392676617202075,
      "portfolio_value": 98283.67870276344
    },
    {
      "date": "2024-08-19",
      "action": 0,
      "position_scale": 0.5,
      "effective_position": 0.0,
      "step_return": 0.0,
      "portfolio_value": 98283.67870276344
    },
    {
      "date": "2024-08-20",
      "action": 0,
      "position_scale": 1.0,
      "effective_position": 0.0,
      "step_return": -0.0,
      "portfolio_value": 98283.67870276344
    },
    {
      "date": "2024-08-21",
      "action": 0,
      "position_scale": 0.5,
      "effective_position": 0.0,
      "step_return": -0.0,
      "portfolio_value": 98283.67870276344
    },
    {
      "date": "2024-08-22",
      "action": 1,
      "position_scale": 1.0,
      "effective_position": 1.0,
      "step_return": 0.0,
      "portfolio_value": 98283.67870276344
    },
    {
      "date": "2024-08-23",
      "action": 1,
      "position_scale": 0.5,
      "effective_position": 0.5,
      "step_return": 0.0014987979350767806,
      "portfolio_value": 98430.98607745489
    },
    {
      "date": "2024-08-26",
      "action": 1,
      "position_scale": 0.5,
      "effective_position": 0.5,
      "step_return": 0.001870795038030789,
      "portfolio_value": 98615.13027779707
    },
    {
      "date": "2024-08-27",
      "action": 1,
      "position_scale": 0.5,
      "effective_position": 0.5,
      "step_return": -0.003376755480428983,
      "portfolio_value": 98282.1310961783
    },
    {
      "date": "2024-08-28",
      "action": 1,
      "position_scale": 0.5,
      "effective_position": 0.5,
      "step_return": 0.007285109478725661,
      "portfolio_value": 98998.12718101642
    },
    {
      "date": "2024-08-29",
      "action": 1,
      "position_scale": 1.0,
      "effective_position": 1.0,
      "step_return": -0.0017189418603633028,
      "portfolio_value": 98827.9551561074
    },
    {
      "date": "2024-08-30",
      "action": 1,
      "position_scale": 0.5,
      "effective_position": 0.5,
      "step_return": -0.027205253670671996,
      "portfolio_value": 96139.31556633172
    },
    {
      "date": "2024-09-03",
      "action": 1,
      "position_scale": 0.5,
      "effective_position": 0.5,
      "step_return": -0.004309413169818161,
      "portfolio_value": 95725.01153369286
    },
    {
      "date": "2024-09-04",
      "action": 1,
      "position_scale": 0.5,
      "effective_position": 0.5,
      "step_return": 0.003463899515757864,
      "portfolio_value": 96056.59335479033
    },
    {
      "date": "2024-09-05",
      "action": 1,
      "position_scale": 0.5,
      "effective_position": 0.5,
      "step_return": -0.003507476386487099,
      "portfolio_value": 95719.677121832
    },
    {
      "date": "2024-09-06",
      "action": 1,
      "position_scale": 0.5,
      "effective_position": 0.5,
      "step_return": 0.00020372508784383738,
      "portfolio_value": 95739.17762146205
    },
    {
      "date": "2024-09-09",
      "action": 1,
      "position_scale": 0.5,
      "effective_position": 0.5,
      "step_return": -0.0018106349434571577,
      "portfolio_value": 95565.82892100279
    },
    {
      "date": "2024-09-10",
      "action": 1,
      "position_scale": 1.0,
      "effective_position": 1.0,
      "step_return": 0.005792551261807366,
      "portfolio_value": 96119.39888390481
    },
    {
      "date": "2024-09-11",
      "action": 1,
      "position_scale": 1.0,
      "effective_position": 1.0,
      "step_return": 0.0004940326689276836,
      "portfolio_value": 96166.88500707116
    },
    {
      "date": "2024-09-12",
      "action": 1,
      "position_scale": 1.0,
      "effective_position": 1.0,
      "step_return": -0.0012120644677647732,
      "portfolio_value": 96050.32454277847
    },
    {
      "date": "2024-09-13",
      "action": 2,
      "position_scale": 0.5,
      "effective_position": -0.5,
      "step_return": -0.02777518726099894,
      "portfolio_value": 93382.50879212307
    },
    {
      "date": "2024-09-16",
      "action": 1,
      "position_scale": 0.5,
      "effective_position": 0.5,
      "step_return": -0.0010862502894194224,
      "portfolio_value": 93281.07201492092
    },
    {
      "date": "2024-09-17",
      "action": 1,
      "position_scale": 1.0,
      "effective_position": 1.0,
      "step_return": 0.008994901744824538,
      "portfolio_value": 94120.12609234704
    },
    {
      "date": "2024-09-18",
      "action": 1,
      "position_scale": 0.5,
      "effective_position": 0.5,
      "step_return": 0.037065710369279116,
      "portfolio_value": 97608.755426006
    },
    {
      "date": "2024-09-19",
      "action": 1,
      "position_scale": 0.5,
      "effective_position": 0.5,
      "step_return": -0.001463760977200708,
      "portfolio_value": 97465.87953878028
    },
    {
      "date": "2024-09-20",
      "action": 1,
      "position_scale": 0.5,
      "effective_position": 0.5,
      "step_return": -0.003790522042553512,
      "portfolio_value": 97096.43297399167
    },
    {
      "date": "2024-09-23",
      "action": 1,
      "position_scale": 0.5,
      "effective_position": 0.5,
      "step_return": 0.0019869679911514886,
      "portfolio_value": 97289.36047836598
    },
    {
      "date": "2024-09-24",
      "action": 1,
      "position_scale": 0.5,
      "effective_position": 0.5,
      "step_return": -0.00219904854706686,
      "portfolio_value": 97075.41645156097
    },
    {
      "date": "2024-09-25",
      "action": 1,
      "position_scale": 0.5,
      "effective_position": 0.5,
      "step_return": 0.0025401384001578985,
      "portfolio_value": 97322.00144460092
    },
    {
      "date": "2024-09-26",
      "action": 1,
      "position_scale": 0.5,
      "effective_position": 0.5,
      "step_return": 0.0005933124392485934,
      "portfolio_value": 97379.74379867056
    },
    {
      "date": "2024-09-27",
      "action": 1,
      "position_scale": 0.5,
      "effective_position": 0.5,
      "step_return": 0.011436029926732623,
      "portfolio_value": 98493.38146300972
    },
    {
      "date": "2024-09-30",
      "action": 1,
      "position_scale": 0.5,
      "effective_position": 0.5,
      "step_return": -0.01457083366594734,
      "portfolio_value": 97058.2507845155
    },
    {
      "date": "2024-10-01",
      "action": 1,
      "position_scale": 0.5,
      "effective_position": 0.5,
      "step_return": 0.0012599001734840986,
      "portfolio_value": 97180.53449151698
    },
    {
      "date": "2024-10-02",
      "action": 1,
      "position_scale": 0.5,
      "effective_position": 0.5,
      "step_return": -0.002447331957446339,
      "portfolio_value": 96942.70146381418
    },
    {
      "date": "2024-10-03",
      "action": 1,
      "position_scale": 0.5,
      "effective_position": 0.5,
      "step_return": 0.0025036425528578523,
      "portfolio_value": 97185.41133638799
    },
    {
      "date": "2024-10-04",
      "action": 1,
      "position_scale": 1.0,
      "effective_position": 1.0,
      "step_return": -0.011265450784623965,
      "portfolio_value": 96090.57386799448
    },
    {
      "date": "2024-10-07",
      "action": 1,
      "position_scale": 0.5,
      "effective_position": 0.5,
      "step_return": 0.018404224510976275,
      "portfolio_value": 97859.0463628496
    },
    {
      "date": "2024-10-08",
      "action": 1,
      "position_scale": 0.5,
      "effective_position": 0.5,
      "step_return": 0.00834915926414932,
      "portfolio_value": 98676.08712637081
    },
    {
      "date": "2024-10-09",
      "action": 1,
      "position_scale": 1.0,
      "effective_position": 1.0,
      "step_return": -0.0010891630965112588,
      "portfolio_value": 98568.61277376463
    },
    {
      "date": "2024-10-10",
      "action": 1,
      "position_scale": 1.0,
      "effective_position": 1.0,
      "step_return": -0.006505321810578387,
      "portfolio_value": 97927.392227249
    },
    {
      "date": "2024-10-11",
      "action": 1,
      "position_scale": 0.5,
      "effective_position": 0.5,
      "step_return": 0.016479748499466366,
      "portfolio_value": 99541.21102236265
    },
    {
      "date": "2024-10-14",
      "action": 1,
      "position_scale": 0.5,
      "effective_position": 0.5,
      "step_return": 0.005512415709632758,
      "portfolio_value": 100089.92355775819
    },
    {
      "date": "2024-10-15",
      "action": 1,
      "position_scale": 0.5,
      "effective_position": 0.5,
      "step_return": -0.004425972897319701,
      "portfolio_value": 99646.92826879675
    },
    {
      "date": "2024-10-16",
      "action": 1,
      "position_scale": 0.5,
      "effective_position": 0.5,
      "step_return": 0.0007981682618214551,
      "portfolio_value": 99726.4632843289
    },
    {
      "date": "2024-10-17",
      "action": 1,
      "position_scale": 0.5,
      "effective_position": 0.5,
      "step_return": 0.006138316692020248,
      "portfolio_value": 100338.61589854323
    },
    {
      "date": "2024-10-18",
      "action": 1,
      "position_scale": 0.5,
      "effective_position": 0.5,
      "step_return": 0.0031488936961539637,
      "portfolio_value": 100654.57153362695
    },
    {
      "date": "2024-10-21",
      "action": 1,
      "position_scale": 0.5,
      "effective_position": 0.5,
      "step_return": -0.0013108557797549259,
      "portfolio_value": 100522.62790677334
    },
    {
      "date": "2024-10-22",
      "action": 1,
      "position_scale": 0.5,
      "effective_position": 0.5,
      "step_return": -0.010811551058102897,
      "portfolio_value": 99435.82238266458
    },
    {
      "date": "2024-10-23",
      "action": 1,
      "position_scale": 0.5,
      "effective_position": 0.5,
      "step_return": -0.00041163063370551034,
      "portfolio_value": 99394.89155208418
    },
    {
      "date": "2024-10-24",
      "action": 1,
      "position_scale": 1.0,
      "effective_position": 1.0,
      "step_return": 0.001821606588265952,
      "portfolio_value": 99575.94994137544
    },
    {
      "date": "2024-10-25",
      "action": 1,
      "position_scale": 1.0,
      "effective_position": 1.0,
      "step_return": 0.008599352944553607,
      "portfolio_value": 100432.23867971053
    },
    {
      "date": "2024-10-28",
      "action": 1,
      "position_scale": 1.0,
      "effective_position": 1.0,
      "step_return": 0.0011567963446841164,
      "portfolio_value": 100548.41832630367
    },
    {
      "date": "2024-10-29",
      "action": 2,
      "position_scale": 1.0,
      "effective_position": -1.0,
      "step_return": -0.015277913071096102,
      "portfolio_value": 99012.2483316782
    },
    {
      "date": "2024-10-30",
      "action": 1,
      "position_scale": 1.0,
      "effective_position": 1.0,
      "step_return": 0.01820948638920925,
      "portfolio_value": 100815.2105200389
    },
    {
      "date": "2024-10-31",
      "action": 1,
      "position_scale": 0.5,
      "effective_position": 0.5,
      "step_return": -0.013279561682817515,
      "portfolio_value": 99476.42871337182
    },
    {
      "date": "2024-11-01",
      "action": 1,
      "position_scale": 1.0,
      "effective_position": 1.0,
      "step_return": -0.002018735374615852,
      "portfolio_value": 99275.61212778768
    },
    {
      "date": "2024-11-04",
      "action": 1,
      "position_scale": 0.5,
      "effective_position": 0.5,
      "step_return": 0.006486057784538825,
      "portfolio_value": 99919.51948464398
    },
    {
      "date": "2024-11-05",
      "action": 1,
      "position_scale": 0.5,
      "effective_position": 0.5,
      "step_return": -0.0016334385014597087,
      "portfolio_value": 99756.30709447041
    },
    {
      "date": "2024-11-06",
      "action": 2,
      "position_scale": 1.0,
      "effective_position": -1.0,
      "step_return": 0.010686043915963143,
      "portfolio_value": 100822.30737297621
    },
    {
      "date": "2024-11-07",
      "action": 0,
      "position_scale": 1.0,
      "effective_position": 0.0,
      "step_return": 0.001188183950158661,
      "portfolio_value": 100942.10282041474
    },
    {
      "date": "2024-11-08",
      "action": 1,
      "position_scale": 1.0,
      "effective_position": 1.0,
      "step_return": -0.0,
      "portfolio_value": 100942.10282041474
    },
    {
      "date": "2024-11-11",
      "action": 1,
      "position_scale": 0.5,
      "effective_position": 0.5,
      "step_return": 0.0,
      "portfolio_value": 100942.10282041474
    },
    {
      "date": "2024-11-12",
      "action": 1,
      "position_scale": 0.5,
      "effective_position": 0.5,
      "step_return": 0.0019845643927342434,
      "portfolio_value": 101142.42892339987
    },
    {
      "date": "2024-11-13",
      "action": 2,
      "position_scale": 0.5,
      "effective_position": -0.5,
      "step_return": 0.006885257230339607,
      "portfolio_value": 101838.82056343881
    },
    {
      "date": "2024-11-14",
      "action": 1,
      "position_scale": 0.5,
      "effective_position": 0.5,
      "step_return": 0.007054615862586785,
      "portfolio_value": 102557.25432241279
    },
    {
      "date": "2024-11-15",
      "action": 1,
      "position_scale": 1.0,
      "effective_position": 1.0,
      "step_return": 0.006711164791186273,
      "portfolio_value": 103245.5329567021
    },
    {
      "date": "2024-11-18",
      "action": 1,
      "position_scale": 0.5,
      "effective_position": 0.5,
      "step_return": 0.001140063349412461,
      "portfolio_value": 103363.23940481659
    },
    {
      "date": "2024-11-19",
      "action": 1,
      "position_scale": 0.5,
      "effective_position": 0.5,
      "step_return": 0.0015770928639269814,
      "portfolio_value": 103526.2528320743
    },
    {
      "date": "2024-11-20",
      "action": 1,
      "position_scale": 0.5,
      "effective_position": 0.5,
      "step_return": -0.001048055875946523,
      "portfolio_value": 103417.75153447893
    },
    {
      "date": "2024-11-21",
      "action": 0,
      "position_scale": 1.0,
      "effective_position": 0.0,
      "step_return": 0.002953758532858281,
      "portfolio_value": 103723.22260052292
    },
    {
      "date": "2024-11-22",
      "action": 1,
      "position_scale": 0.5,
      "effective_position": 0.5,
      "step_return": 0.0,
      "portfolio_value": 103723.22260052292
    },
    {
      "date": "2024-11-25",
      "action": 1,
      "position_scale": 1.0,
      "effective_position": 1.0,
      "step_return": 0.004702224923712581,
      "portfolio_value": 104210.95252300288
    },
    {
      "date": "2024-11-26",
      "action": 0,
      "position_scale": 1.0,
      "effective_position": 0.0,
      "step_return": -0.0005531551775520426,
      "portfolio_value": 104153.30769505716
    },
    {
      "date": "2024-11-27",
      "action": 2,
      "position_scale": 0.5,
      "effective_position": -0.5,
      "step_return": 0.0,
      "portfolio_value": 104153.30769505716
    },
    {
      "date": "2024-11-29",
      "action": 1,
      "position_scale": 0.5,
      "effective_position": 0.5,
      "step_return": -0.004761248771426185,
      "portfolio_value": 103657.4078867541
    },
    {
      "date": "2024-12-02",
      "action": 1,
      "position_scale": 1.0,
      "effective_position": 1.0,
      "step_return": 0.00638592188076415,
      "portfolio_value": 104319.35599588143
    },
    {
      "date": "2024-12-03",
      "action": 1,
      "position_scale": 0.5,
      "effective_position": 0.5,
      "step_return": 0.0014836956604209735,
      "portfolio_value": 104474.13417167043
    },
    {
      "date": "2024-12-04",
      "action": 1,
      "position_scale": 0.5,
      "effective_position": 0.5,
      "step_return": 6.171328192306542e-05,
      "portfolio_value": 104480.58161336624
    },
    {
      "date": "2024-12-05",
      "action": 1,
      "position_scale": 0.5,
      "effective_position": 0.5,
      "step_return": -0.00041145527336619966,
      "portfolio_value": 104437.59252709706
    },
    {
      "date": "2024-12-06",
      "action": 1,
      "position_scale": 1.0,
      "effective_position": 1.0,
      "step_return": 0.00805055022659734,
      "portfolio_value": 105278.37261128136
    },
    {
      "date": "2024-12-09",
      "action": 1,
      "position_scale": 1.0,
      "effective_position": 1.0,
      "step_return": 0.004133767327917728,
      "portfolio_value": 105713.56890831824
    },
    {
      "date": "2024-12-10",
      "action": 1,
      "position_scale": 0.5,
      "effective_position": 0.5,
      "step_return": -0.0051659994276031275,
      "portfolio_value": 105167.45267184799
    },
    {
      "date": "2024-12-11",
      "action": 1,
      "position_scale": 1.0,
      "effective_position": 1.0,
      "step_return": 0.0029818180460164673,
      "portfolio_value": 105481.04288007849
    },
    {
      "date": "2024-12-12",
      "action": 1,
      "position_scale": 0.5,
      "effective_position": 0.5,
      "step_return": 0.0006856817013815973,
      "portfolio_value": 105553.36930102401
    },
    {
      "date": "2024-12-13",
      "action": 1,
      "position_scale": 0.5,
      "effective_position": 0.5,
      "step_return": 0.005863779980337721,
      "portfolio_value": 106172.31103478855
    },
    {
      "date": "2024-12-16",
      "action": 1,
      "position_scale": 0.5,
      "effective_position": 0.5,
      "step_return": 0.004859812558643032,
      "portfolio_value": 106688.28856533556
    },
    {
      "date": "2024-12-17",
      "action": 1,
      "position_scale": 1.0,
      "effective_position": 1.0,
      "step_return": -0.010710871828760177,
      "portfolio_value": 105545.56398088248
    },
    {
      "date": "2024-12-18",
      "action": 1,
      "position_scale": 0.5,
      "effective_position": 0.5,
      "step_return": 0.007014646628176783,
      "portfolio_value": 106285.92881538
    },
    {
      "date": "2024-12-19",
      "action": 1,
      "position_scale": 0.5,
      "effective_position": 0.5,
      "step_return": 0.009407911421307528,
      "portfolio_value": 107285.85741900648
    },
    {
      "date": "2024-12-20",
      "action": 1,
      "position_scale": 0.5,
      "effective_position": 0.5,
      "step_return": 0.0015324660652511028,
      "portfolio_value": 107450.26935478249
    },
    {
      "date": "2024-12-23",
      "action": 1,
      "position_scale": 0.5,
      "effective_position": 0.5,
      "step_return": 0.005739134992054263,
      "portfolio_value": 108066.94095554219
    },
    {
      "date": "2024-12-24",
      "action": 1,
      "position_scale": 0.5,
      "effective_position": 0.5,
      "step_return": 0.0015878105208817109,
      "portfolio_value": 108238.5307813509
    },
    {
      "date": "2024-12-26",
      "action": 1,
      "position_scale": 0.5,
      "effective_position": 0.5,
      "step_return": -0.006621104610651198,
      "portfolio_value": 107521.87214614438
    },
    {
      "date": "2024-12-27",
      "action": 1,
      "position_scale": 0.5,
      "effective_position": 0.5,
      "step_return": -0.0066317149039688906,
      "portfolio_value": 106808.81774413015
    }
  ]
}